MANIFEST.in
README.md
setup.cfg
setup.py
version.txt
django_gocs/__init__.py
django_gocs.egg-info/PKG-INFO
django_gocs.egg-info/SOURCES.txt
django_gocs.egg-info/dependency_links.txt
django_gocs.egg-info/requires.txt
django_gocs.egg-info/top_level.txt