Metadata-Version: 1.0
Name: django-gocs
Version: 0.0.1
Summary: Django file storage backend and temporary file handler for Google Cloud Storage
Home-page: https://github.com/odin-public/django-gocs
Author: APS Lite team
Author-email: aps@odin.com
License: UNKNOWN
Keywords: django,storage,gcs,google cloud storage
Platform: UNKNOWN
